voxly/__init__.py
voxly/boundary.py
voxly/chunk.py
voxly/faces.py
voxly/grid.py
voxly/index_dict.py
voxly/iterators.py
voxly/typing.py
voxly-0.0.1.dist-info/LICENSE
voxly-0.0.1.dist-info/WHEEL
voxly-0.0.1.dist-info/METADATA
voxly-0.0.1.dist-info/RECORD
